{
  "questIDHigh:4": 0,
  "preRequisites:9": {
    "0:10": {
      "questIDHigh:4": 0,
      "questIDLow:4": 40
    }
  },
  "questIDLow:4": 50,
  "properties:10": {
    "betterquesting:10": {
      "snd_complete:8": "random.levelup",
      "taskLogic:8": "AND",
      "visibility:8": "NORMAL",
      "isMain:1": 0,
      "simultaneous:1": 0,
      "icon:10": {
        "id:8": "minecraft:sapling",
        "Count:3": 1,
        "Damage:2": 2,
        "OreDict:8": ""
      },
      "snd_update:8": "random.levelup",
      "repeatTime:3": -1,
      "globalShare:1": 0,
      "questLogic:8": "AND",
      "repeat_relative:1": 1,
      "name:8": "[3] Советы Доктора Попова",
      "lockedProgress:1": 0,
      "autoClaim:1": 0,
      "isSilent:1": 0,
      "desc:8": "Это живой саженец. Размер его должен быть примерно, как толщина большого пальца.\n\nЕго нужно очистить, посадить в землю, чтобы вы могли §aне отрывая от ботвы§r зажать §6Ctrl§r (или другую кнопку для спринта) и бегать вокруг саженца, прыгая и приседая.\n\nЭто даст вам прохладу, влажность и, скорее всего, §aсилу земли§r. §mА для дополнительной эффективности, можно снять процесс на камеру и выложить на ютубчик.§r\n\nНа самом деле, вам это ничего не даст, а вот саженец от такой магии реально начнет расти быстрее."
    }
  },
  "tasks:9": {
    "0:10": {
      "index:3": 0,
      "taskID:8": "bq_standard:checkbox"
    }
  },
  "rewards:9": {
    "0:10": {
      "rewardID:8": "bq_standard:choice",
      "index:3": 0,
      "choices:9": {
        "0:10": {
          "id:8": "minecraft:sapling",
          "Count:3": 1,
          "Damage:2": 0,
          "OreDict:8": ""
        },
        "1:10": {
          "id:8": "minecraft:sapling",
          "Count:3": 1,
          "Damage:2": 1,
          "OreDict:8": ""
        },
        "2:10": {
          "id:8": "minecraft:sapling",
          "Count:3": 1,
          "Damage:2": 2,
          "OreDict:8": ""
        }
      }
    }
  }
}